.coveragerc
.gitignore
.travis.yml
LICENSE.txt
README.md
README.pypi
codecov.yml
installation_template.sh
requirements.txt
setup.cfg
setup.py
Orange3_Recommendation.egg-info/PKG-INFO
Orange3_Recommendation.egg-info/SOURCES.txt
Orange3_Recommendation.egg-info/dependency_links.txt
Orange3_Recommendation.egg-info/entry_points.txt
Orange3_Recommendation.egg-info/namespace_packages.txt
Orange3_Recommendation.egg-info/not-zip-safe
Orange3_Recommendation.egg-info/requires.txt
Orange3_Recommendation.egg-info/top_level.txt
doc/Makefile
doc/make.bat
doc/source/conf.py
doc/source/index.rst
doc/source/performance/benchmarks.rst
doc/source/resources/icons/average.svg
doc/source/resources/icons/brismf.svg
doc/source/resources/icons/climf.svg
doc/source/resources/icons/item-avg.svg
doc/source/resources/icons/svdplusplus.svg
doc/source/resources/icons/trustsvd.svg
doc/source/resources/icons/user-avg.svg
doc/source/resources/icons/user-item-baseline.svg
doc/source/resources/images/example_baselines.png
doc/source/resources/images/example_latent_factor_models.png
doc/source/scripting/baseline.rst
doc/source/scripting/optimizers.rst
doc/source/scripting/ranking.rst
doc/source/scripting/rating.rst
doc/source/scripting/baselines/globalavg.rst
doc/source/scripting/baselines/itemavg.rst
doc/source/scripting/baselines/useravg.rst
doc/source/scripting/baselines/useritembaseline.rst
doc/source/scripting/ranking/climf.rst
doc/source/scripting/rating/brismf.rst
doc/source/scripting/rating/svdplusplus.rst
doc/source/scripting/rating/trustsvd.rst
doc/source/user/faq.rst
doc/source/user/installation.rst
doc/source/user/tutorial.rst
doc/source/user/code/movielens100k.tab
doc/source/user/code/ratings.tab
doc/source/widgets/baselines.rst
doc/source/widgets/brismf.rst
doc/source/widgets/svdplusplus.rst
doc/source/widgets/trustsvd.rst
doc/source/widgets/disabled/_climf
orangecontrib/__init__.py
orangecontrib/recommendation/__init__.py
orangecontrib/recommendation/base_recommendation.py
orangecontrib/recommendation/baseline/__init__.py
orangecontrib/recommendation/baseline/global_avg.py
orangecontrib/recommendation/baseline/item_avg.py
orangecontrib/recommendation/baseline/user_avg.py
orangecontrib/recommendation/baseline/user_item_baseline.py
orangecontrib/recommendation/datasets/binary_data.tab
orangecontrib/recommendation/datasets/binary_data_dis.tab
