Metadata-Version: 1.1
Name: Orange3-Recommendation
Version: 0.1.3
Summary: Orange3 add-on for recommender systems
Home-page: https://github.com/biolab/orange3-recommendation
Author: Bioinformatics Laboratory, FRI UL
Author-email: contact@orange.biolab.si
License: UNKNOWN
Download-URL: https://github.com/biolab/orange3-recommendation/tarball/0.1.3
Keywords: orange3-recommendation,data mining,orange3 add-on
Platform: UNKNOWN
